src/__init__.py
src/__version__.py
src/grid.py
src/heuristics.py
src/interfaces.py
src/mytypes/__init__.py
src/mytypes/mytypes.py
src/mytypes/walkable.py
src/node.py
src/path.py
src/pathfinder.py
src/properties.py
src/search/__init__.py
src/search/astar.py
src/search/bfs.py
src/search/dfs.py
src/search/dijkstra.py
src/search/jps.py
src/search/thetastar.py
src/utils.py
jumper_py-0.2.2.dist-info/WHEEL
jumper_py-0.2.2.dist-info/METADATA
jumper_py-0.2.2.dist-info/RECORD
