Metadata-Version: 2.1
Name: jumper-py
Version: 0.2.2
Summary: 
Author: David
Author-email: davigetto@gmail.com
Requires-Python: >=3.8,<4.0
Classifier: Programming Language :: Python :: 3
Classifier: Programming Language :: Python :: 3.8
Classifier: Programming Language :: Python :: 3.9
Requires-Dist: pyprof2calltree (>=1.4.5,<2.0.0)
